devtools_cron_parser/__init__.py
devtools_cron_parser-1.0.1.dist-info/METADATA
devtools_cron_parser-1.0.1.dist-info/WHEEL
devtools_cron_parser-1.0.1.dist-info/top_level.txt
devtools_cron_parser-1.0.1.dist-info/RECORD
