Metadata-Version: 2.1
Name: devtools-cron-parser
Version: 1.0.1
Summary: Cron expression parser
Home-page: https://devtools.at/tools/cron-parser
Author: DevTools.at
Author-email: hello@devtools.at
Project-URL: Homepage, https://devtools.at/tools/cron-parser
Project-URL: Repository, https://github.com/devtools-at/cron-parser
Classifier: Development Status :: 4 - Beta
Classifier: Intended Audience :: Developers
Classifier: License :: OSI Approved :: MIT License
Classifier: Programming Language :: Python :: 3
Requires-Python: >=3.8
